web_alert/__init__.py
web_alert/config.py
web_alert/dashboard.py
web_alert/core/__init__.py
web_alert/core/alerter.py
web_alert/core/detector.py
web_alert/core/monitor_job.py
web_alert/core/scraper.py
web_alert/data/__init__.py
web_alert/data/database.py
web_alert/icons/icon.ico
web_alert/icons/icon.png
web_alert/migrations/__init__.py
web_alert/migrations/migration_manager.py
web_alert/migrations/versions/001_add_tts_message.py
web_alert/migrations/versions/__init__.py
web_alert/models/__init__.py
web_alert/models/active_job.py
web_alert/models/app_settings.py
web_alert/models/base.py
web_alert/models/configuration.py
web_alert/services/__init__.py
web_alert/services/history_manager.py
web_alert/services/job_manager.py
web_alert/services/theme_manager.py
web_alert/sounds/alert.wav
web_alert/ui/__init__.py
web_alert/ui/add_job_dialog.py
web_alert/ui/dashboard.py
web_alert/ui/edit_job_dialog.py
web_alert/ui/job_log_viewer.py
web_alert/utils/__init__.py
web_alert/utils/generate_sound.py
web_alert/utils/logging_config.py
web_alert/utils/window_utils.py
web_alert-1.1.1.data/data/web_alert/icons/icon.ico
web_alert-1.1.1.data/data/web_alert/icons/icon.png
web_alert-1.1.1.dist-info/METADATA
web_alert-1.1.1.dist-info/WHEEL
web_alert-1.1.1.dist-info/entry_points.txt
web_alert-1.1.1.dist-info/licenses/LICENSE
web_alert-1.1.1.dist-info/RECORD
