Metadata-Version: 2.4
Name: web-alert
Version: 1.1.1
Summary: Modern web monitoring and alert system with customizable GUI for tracking website changes
Project-URL: Homepage, https://github.com/Almas-Ali/web-alert
Project-URL: Repository, https://github.com/Almas-Ali/web-alert
Project-URL: Issues, https://github.com/Almas-Ali/web-alert/issues
Project-URL: Documentation, https://github.com/Almas-Ali/web-alert#readme
Author-email: "Md. Almas Ali" <almaspr3@gmail.com>
Maintainer-email: "Md. Almas Ali" <almaspr3@gmail.com>
License: MIT
License-File: LICENSE
Keywords: alert-system,change-detection,customtkinter,gui,web-monitoring,web-scraper,website-tracker
Classifier: Development Status :: 4 - Beta
Classifier: Intended Audience :: Developers
Classifier: Intended Audience :: End Users/Desktop
Classifier: License :: OSI Approved :: MIT License
Classifier: Operating System :: Microsoft :: Windows
Classifier: Programming Language :: Python :: 3
Classifier: Programming Language :: Python :: 3.10
Classifier: Programming Language :: Python :: 3.11
Classifier: Programming Language :: Python :: 3.12
Classifier: Programming Language :: Python :: 3.13
Classifier: Topic :: Internet :: WWW/HTTP :: Dynamic Content
Classifier: Topic :: System :: Monitoring
Classifier: Topic :: Utilities
Requires-Python: >=3.10
Requires-Dist: beautifulsoup4>=4.12.0
Requires-Dist: customtkinter>=5.2.0
Requires-Dist: lxml>=4.9.0
Requires-Dist: pyttsx3>=2.90
Requires-Dist: pywin32>=311; sys_platform == 'win32'
Requires-Dist: requests>=2.31.0
Requires-Dist: sqlalchemy>=2.0.0
